climacell_api.py
climacell_api/__init__.py
climacell_api/client.py
climacell_api/climacell_api.py
climacell_api/climacell_response.py
climacell_api/conftest.py
climacell_python-0.0.7.dist-info/LICENSE
climacell_python-0.0.7.dist-info/METADATA
climacell_python-0.0.7.dist-info/WHEEL
climacell_python-0.0.7.dist-info/top_level.txt
climacell_python-0.0.7.dist-info/RECORD
