Metadata-Version: 2.1
Name: climacell-python
Version: 0.0.7
Summary: Python library to interface with the ClimaCell Weather API
Home-page: https://github.com/nicolo/climacell-python
Author: Nicolo Giorgi
Author-email: nicolo.giorgi@gmail.com
License: UNKNOWN
Platform: UNKNOWN
Classifier: Programming Language :: Python :: 3.5
Classifier: Programming Language :: Python :: 3.6
Classifier: Programming Language :: Python :: 3.7
Classifier: Programming Language :: Python :: 3.8
Classifier: License :: OSI Approved :: MIT License
Classifier: Operating System :: OS Independent
Provides-Extra: dev
